yaml_mako.py
yaml_mako-1.0.0.dist-info/METADATA
yaml_mako-1.0.0.dist-info/WHEEL
yaml_mako-1.0.0.dist-info/top_level.txt
yaml_mako-1.0.0.dist-info/RECORD
