Metadata-Version: 2.1
Name: yaml-mako
Version: 1.0.0
Summary: use mako templating in your YAML files
Home-page: https://github.com/haarcuba/yaml_mako
Author: Yoav Kleinberger
Author-email: haarcuba@gmail.com
License: UNKNOWN
Keywords: yaml,mako,templating
Platform: UNKNOWN
Classifier: Programming Language :: Python
Requires-Dist: pyyaml
Requires-Dist: mako
